chiahub_monitor/__init__.py
chiahub_monitor/client.py
chiahub_monitor/main.py
chiahub_monitor-0.0.5.dist-info/LICENSE
chiahub_monitor-0.0.5.dist-info/METADATA
chiahub_monitor-0.0.5.dist-info/WHEEL
chiahub_monitor-0.0.5.dist-info/top_level.txt
chiahub_monitor-0.0.5.dist-info/RECORD
