Metadata-Version: 2.1
Name: chiahub-monitor
Version: 0.0.5
Summary: A monitoring utility for chia blockchain
Home-page: https://github.com/yan74/chiahub-monitor
Author: Yan Hackl-Feldbusch
Author-email: yan@cryptico.io
License: UNKNOWN
Project-URL: Bug Tracker, https://github.com/yan74/chiahub-monitor/issues
Platform: UNKNOWN
Classifier: Programming Language :: Python :: 3
Classifier: License :: OSI Approved :: MIT License
Classifier: Operating System :: OS Independent
License-File: LICENSE
Requires-Dist: setuptools (~=57.0.0)
Requires-Dist: aiohttp (~=3.7.4)
Requires-Dist: PyYAML (~=5.4.1)
